src/__init__.py
src/labs/CYBE-M01D01-cron-and-more/docker-compose.prod.yaml
src/labs/CYBE-M01D01-my-first-ctf/docker-compose.prod.yaml
src/labs/CYBE-M01D01-processes/docker-compose.prod.yaml
src/labs/CYBE-M01D01-user-management/docker-compose.prod.yaml
src/labs/CYBE-M01D02-cron-jobs/docker-compose.prod.yaml
src/labs/CYBE-M01D02-permission-ctf/docker-compose.prod.yaml
src/labs/CYBE-M02D01-osi-i-to-iv/docker-compose.prod.yaml
src/labs/CYBE-M02D02-nmap-ctf/docker-compose.prod.yaml
src/labs/CYBE-M03D01-imdb-db/docker-compose.prod.yaml
src/labs/CYBE-M03D01-weblab/docker-compose.prod.yaml
src/labs/CYBE-M03D02-vuln-web-app/docker-compose.prod.yaml
src/labs/CYBE-M04-little-big-ctf/docker-compose.prod.yaml
src/labs/CYBE-M05-rs6092/docker-compose.prod.yaml
src/labs/CYBFS-M04-sql-ex/docker-compose.prod.yaml
src/labs/CYBFS-M04D02-sql-misconf/docker-compose.prod.yaml
src/labs/CYBFS-M05-dvwa/docker-compose.prod.yaml
src/labs/CYBFS-M05D02-template-injection/docker-compose.prod.yaml
src/labs/CYBFS-M05D03-csrf-demo/docker-compose.prod.yaml
src/labs/CYBFS-M05D03-csrf-password-change/docker-compose.prod.yaml
src/labs/CYBFS-M05D03-jwt-auth-bypass/docker-compose.prod.yaml
src/labs/CYBFS-M05D03-jwt-integrity/docker-compose.prod.yaml
src/labs/CYBFS-M08D01-exploit-user/docker-compose.prod.yaml
src/labs/CYBFS-M08D01-sudo1/docker-compose.prod.yaml
src/labs/CYBFS-M08D01-suid2/docker-compose.prod.yaml
src/labs/CYBFS-M08D02-linux-privesc/docker-compose.prod.yaml
src/labs/CYBFS-M08D02-suid/docker-compose.prod.yaml
src/labs/CYBFS-M08D05-docker-evasion/docker-compose.prod.yaml
src/labs/CYBFS-M08D07-ldap-compromission/docker-compose.prod.yaml
src/labs/CYBFS-M09D01-manual-audit/docker-compose.prod.yaml
src/labs/CYBFS-M09D04-windows-box/docker-compose.prod.yaml
src/labs/CYBFS-M15D01-msf1/docker-compose.prod.yaml
src/labs/CYBFS-M15D01-msf2/docker-compose.prod.yaml
src/labs/CYBL-M03D03-ibc-web-app/docker-compose.prod.yaml
src/labs/CYBL-M03D05-ibc-news/docker-compose.prod.yaml
jedha_cli-3.1.0.dist-info/METADATA
jedha_cli-3.1.0.dist-info/WHEEL
jedha_cli-3.1.0.dist-info/entry_points.txt
jedha_cli-3.1.0.dist-info/licenses/LICENSE
jedha_cli-3.1.0.dist-info/RECORD
