Metadata-Version: 2.4
Name: jedha-cli
Version: 3.1.0
Summary: A CLI to start cybersecurity labs and practice your skills
License-File: LICENSE
Author: ademenet
Author-email: alain@jedha.co
Requires-Python: >=3.10,<4.0
Classifier: Programming Language :: Python :: 3
Classifier: Programming Language :: Python :: 3.10
Classifier: Programming Language :: Python :: 3.11
Classifier: Programming Language :: Python :: 3.12
Classifier: Programming Language :: Python :: 3.13
Classifier: Programming Language :: Python :: 3.14
Requires-Dist: click (==8.1.8)
Requires-Dist: pyyaml (>=6.0.1,<7.0.0)
Requires-Dist: requests (>=2.31.0,<3.0.0)
Requires-Dist: setuptools
Requires-Dist: typer[all] (>=0.9.0,<0.10.0)
